[
    {  "name": "Adelaide Chan", "photo": "Images/1.jpg" },
    {  "name": "Alexis Chan", "photo": "Images/2.jpg" },
    {  "name": "Chan Chin (Kiwie)", "photo": "Images/3.jpg" },
    {  "name": "Chan Doria", "photo": "Images/4.jpg" },
    {  "name": "Chloe Chan", "photo": "Images/5.jpg" },
    {  "name": "Atarah Cheng", "photo": "Images/6.jpg" },
    {  "name": "Zoey Cheng", "photo": "Images/7.jpg" },
    {  "name": "Cheng Tsz Kiu (Alyssa)", "photo": "Images/8.jpg" },
    {  "name": "Cheng Yuen Wing (Karlie)", "photo": "Images/9.jpg"},
    {  "name":"Mian Cheung","photo":"Images/10.jpg"},
    {  "name":"Sophie Chiu","photo":"Images/11.jpg"},
    {  "name":"Fong Hay Lam (Kayla)","photo":"Images/12.jpg"},
    {  "name":"Glory Fong","photo":"Images/13.jpg"},
    {  "name":"Chloe Fung","photo":"Images/14.jpg"},
    {  "name":"Hau Yi Ting","photo":"Images/15.jpg"},
    {  "name":"Kot Wing Lam (Sheena)","photo":"Images/16.jpg"},
    {  "name":"Hailey Lam","photo":"Images/17.jpg"},
    {  "name":"Meagan Lam","photo":"Images/18.jpg"},
    {  "name":"Lam Yu Tsit (Gianna)","photo":"Images/19.jpg"},
    {  "name":"Lau Cheuk Yau (Tiana)","photo":"Images/20.jpg"},
    {  "name":"Lau Sin Yee (Brielle)","photo":"Images/21.jpg"},
    {  "name":"Jacqueline Leung","photo":"Images/22.jpg"},
    {  "name":"Juno Li","photo":"Images/23.jpg"},
    {  "name":"Lo Chin Yu (Charlie)","photo":"Images/24.jpg"},
    {  "name":"Karley Lo","photo":"Images/25.jpg"},
    {  "name":"Sin Yan Yin (Hanna)","photo":"Images/26.jpg"},
    {  "name":"Valerie Tang","photo":"Images/27.jpg"},
    {  "name":"To Chin Yuet","photo":"Images/28.jpg"},
    {  "name":"Tsang Po Che","photo":"Images/29.jpg"},
    {  "name":"Tsui Sum Wing (Acadia)","photo":"Images/30.jpg"},
    {  "name":"Adelyn Wong","photo":"Images/31.jpg"},
    {  "name":"Hannah Wong","photo":"Images/32.jpg"},
    {  "name":"Jeannie Wong","photo":"Images/33.jpg"},
    {  "name":"Wong Wing Lam","photo":"Images/34.jpg"},
    {  "name":"Jessalyn Yim","photo":"Images/35.jpg"},
    {  "name":"Yip Pui Lam","photo":"Images/36.jpg"}
]